collective.shariff-3.0.0-py3.10-nspkg.pth
collective/shariff/__init__.py
collective/shariff/browser.py
collective/shariff/configure.zcml
collective/shariff/decorator.py
collective/shariff/interfaces.py
collective/shariff/setuphandlers.py
collective/shariff/testing.py
collective/shariff/upgrades.zcml
collective/shariff/viewlet.pt
collective/shariff/profiles/default/browserlayer.xml
collective/shariff/profiles/default/metadata.xml
collective/shariff/profiles/default/registry.xml
collective/shariff/profiles/uninstall/browserlayer.xml
collective/shariff/profiles/uninstall/registry.xml
collective/shariff/resources/fa-brands-400.eot
collective/shariff/resources/fa-brands-400.svg
collective/shariff/resources/fa-brands-400.ttf
collective/shariff/resources/fa-brands-400.woff
collective/shariff/resources/fa-brands-400.woff2
collective/shariff/resources/fa-regular-400.eot
collective/shariff/resources/fa-regular-400.svg
collective/shariff/resources/fa-regular-400.ttf
collective/shariff/resources/fa-regular-400.woff
collective/shariff/resources/fa-regular-400.woff2
collective/shariff/resources/fa-solid-900.eot
collective/shariff/resources/fa-solid-900.svg
collective/shariff/resources/fa-solid-900.ttf
collective/shariff/resources/fa-solid-900.woff
collective/shariff/resources/fa-solid-900.woff2
collective/shariff/resources/shariff.complete.css
collective/shariff/resources/shariff.complete.js
collective/shariff/resources/shariff.min.css
collective/shariff/resources/shariff.min.js
collective/shariff/tests/__init__.py
collective/shariff/tests/test_setup.py
collective.shariff-3.0.0.dist-info/LICENSE.GPL
collective.shariff-3.0.0.dist-info/LICENSE.txt
collective.shariff-3.0.0.dist-info/METADATA
collective.shariff-3.0.0.dist-info/WHEEL
collective.shariff-3.0.0.dist-info/entry_points.txt
collective.shariff-3.0.0.dist-info/namespace_packages.txt
collective.shariff-3.0.0.dist-info/top_level.txt
collective.shariff-3.0.0.dist-info/RECORD
