Metadata-Version: 2.1
Name: collective.shariff
Version: 3.0.0
Summary: Implement shariff - social media buttons with privacy
Home-page: https://github.com/collective/collective.shariff
Author: petschki
Author-email: peter.mathis@kominat.at
License: GPL
Keywords: plone social sharing shariff
Classifier: Development Status :: 5 - Production/Stable
Classifier: Environment :: Web Environment
Classifier: Framework :: Plone
Classifier: Framework :: Plone :: Addon
Classifier: Framework :: Plone :: 6.0
Classifier: License :: OSI Approved :: GNU General Public License v2 (GPLv2)
Classifier: Operating System :: OS Independent
Classifier: Programming Language :: Python
Classifier: Programming Language :: Python :: 3.8
Classifier: Programming Language :: Python :: 3.9
Classifier: Programming Language :: Python :: 3.10
Classifier: Topic :: Software Development :: Libraries :: Python Modules
License-File: LICENSE.GPL
License-File: LICENSE.txt
Requires-Dist: setuptools
Requires-Dist: plone.api (>=1.5)
Provides-Extra: test
Requires-Dist: plone.app.testing ; extra == 'test'
Requires-Dist: plone.app.contenttypes ; extra == 'test'
Requires-Dist: plone.app.robotframework ; extra == 'test'
Requires-Dist: robotframework-selenium2library ; extra == 'test'
